{
  "code-reviewer": {
    "url": "https://github.com/LucasHua/giscus-voting-demo/discussions/2",
    "reactions": {
      "ROCKET": 1,
      "HEART": 1,
      "THUMBS_DOWN": 1,
      "CONFUSED": 0,
      "LAUGH": 0,
      "THUMBS_UP": 1,
      "EYES": 1,
      "HOORAY": 0
    }
  },
  "sfi-dev-toolkit": {
    "url": "https://github.com/LucasHua/giscus-voting-demo/discussions/4",
    "reactions": {
      "ROCKET": 0,
      "HEART": 1,
      "THUMBS_DOWN": 1,
      "CONFUSED": 0,
      "LAUGH": 0,
      "THUMBS_UP": 1,
      "EYES": 1,
      "HOORAY": 0
    }
  },
  "rubber-duck": {
    "url": "https://github.com/LucasHua/giscus-voting-demo/discussions/3",
    "reactions": {
      "ROCKET": 0,
      "HEART": 1,
      "THUMBS_DOWN": 1,
      "CONFUSED": 0,
      "LAUGH": 1,
      "THUMBS_UP": 1,
      "EYES": 0,
      "HOORAY": 0
    }
  },
  "bug-fixer": {
    "url": "https://github.com/LucasHua/giscus-voting-demo/discussions/1",
    "reactions": {
      "ROCKET": 0,
      "HEART": 1,
      "THUMBS_DOWN": 1,
      "CONFUSED": 0,
      "LAUGH": 0,
      "THUMBS_UP": 1,
      "EYES": 0,
      "HOORAY": 0
    }
  },
  "deep-review": {
    "url": "https://github.com/LucasHua/giscus-voting-demo/discussions/5",
    "reactions": {
      "ROCKET": 0,
      "HEART": 1,
      "THUMBS_DOWN": 1,
      "CONFUSED": 0,
      "LAUGH": 0,
      "THUMBS_UP": 1,
      "EYES": 1,
      "HOORAY": 0
    }
  }
}
